jinja2_custom_filters_extension/__init__.py
jinja2_custom_filters_extension/string_filters_extension.py
tests/__init__.py
tests/test_string_filter_extension.py
jinja2_custom_filters_extension-0.0.2.dist-info/LICENSE
jinja2_custom_filters_extension-0.0.2.dist-info/METADATA
jinja2_custom_filters_extension-0.0.2.dist-info/WHEEL
jinja2_custom_filters_extension-0.0.2.dist-info/top_level.txt
jinja2_custom_filters_extension-0.0.2.dist-info/RECORD
