Metadata-Version: 2.1
Name: jinja2-custom-filters-extension
Version: 0.0.2
Summary: A package containing custom filters for jinja2
Home-page: https://github.com/Harish-Sridhar/jinja2-custom-filters-extension
Author: Harish Sridhar
Author-email: harish.18.sridhar@gmail.com
License: UNKNOWN
Platform: UNKNOWN
Classifier: Programming Language :: Python :: 3
Classifier: License :: OSI Approved :: MIT License
Classifier: Operating System :: OS Independent
Requires-Python: >=3.6
